[{"position":"1","positionText":"1","points":"45","wins":"5","Constructor":{"constructorId":"ferrari","url":"https://en.wikipedia.org/wiki/Scuderia_Ferrari","name":"Ferrari","nationality":"Italian"}},{"position":"2","positionText":"2","points":"35","wins":"3","Constructor":{"constructorId":"lotus-climax","url":"https://en.wikipedia.org/wiki/Team_Lotus","name":"Lotus-Climax","nationality":"British"}},{"position":"3","positionText":"3","points":"22","wins":"0","Constructor":{"constructorId":"porsche","url":"https://en.wikipedia.org/wiki/Porsche_in_motorsport","name":"Porsche","nationality":"German"}},{"position":"4","positionText":"4","points":"14","wins":"0","Constructor":{"constructorId":"cooper-climax","url":"https://en.wikipedia.org/wiki/Cooper_Car_Company","name":"Cooper-Climax","nationality":"British"}},{"position":"5","positionText":"5","points":"7","wins":"0","Constructor":{"constructorId":"brm","url":"https://en.wikipedia.org/wiki/British_Racing_Motors","name":"BRM","nationality":"British"}},{"positionText":"-","points":"0","wins":"0","Constructor":{"constructorId":"cooper-maserati","url":"https://en.wikipedia.org/wiki/Cooper_Car_Company","name":"Cooper-Maserati","nationality":"British"}},{"positionText":"-","points":"0","wins":"0","Constructor":{"constructorId":"gilby","url":"https://en.wikipedia.org/wiki/Gilby","name":"Gilby","nationality":"British"}},{"positionText":"-","points":"0","wins":"0","Constructor":{"constructorId":"lotus-maserati","url":"https://en.wikipedia.org/wiki/Team_Lotus","name":"Lotus-Maserati","nationality":"British"}},{"positionText":"-","points":"0","wins":"0","Constructor":{"constructorId":"ferguson","url":"https://en.wikipedia.org/wiki/Ferguson_Research","name":"Ferguson","nationality":"British"}},{"positionText":"-","points":"0","wins":"0","Constructor":{"constructorId":"de_tomaso-alfa_romeo","url":"https://en.wikipedia.org/wiki/De_Tomaso","name":"De Tomaso-Alfa Romeo","nationality":"Italian"}},{"positionText":"-","points":"0","wins":"0","Constructor":{"constructorId":"de_tomaso-osca","url":"https://en.wikipedia.org/wiki/De_Tomaso","name":"De Tomaso-Osca","nationality":"Italian"}},{"positionText":"-","points":"0","wins":"0","Constructor":{"constructorId":"jbw","url":"https://en.wikipedia.org/wiki/JBW","name":"JBW","nationality":"British"}},{"positionText":"-","points":"0","wins":"0","Constructor":{"constructorId":"emeryson","url":"https://en.wikipedia.org/wiki/Emeryson","name":"Emeryson","nationality":"British"}},{"positionText":"-","points":"0","wins":"0","Constructor":{"constructorId":"mbm","url":"https://en.wikipedia.org/wiki/Monteverdi_(automobile)","name":"MBM","nationality":"Swiss"}}]